[
  {
    "filter": {
      "metadata.shufersal_id": "P_7290112338877"
    },
    "update": {
      "$set": {
        "name_en": "Ski Strawberry",
        "aliases.en": [
          "Ski Strawberry"
        ],
        "aliases.ar": [],
        "brand_en": "Ski"
      }
    }
  },
  {
    "filter": {
      "metadata.shufersal_id": "P_7290110573812"
    },
    "update": {
      "$set": {
        "name_en": "",
        "aliases.en": [
          ""
        ],
        "aliases.ar": []
      }
    }
  },
  {
    "filter": {
      "metadata.shufersal_id": "P_7290112339867"
    },
    "update": {
      "$set": {
        "name_en": "Strawberry",
        "aliases.en": [
          "Strawberry"
        ],
        "aliases.ar": []
      }
    }
  },
  {
    "filter": {
      "metadata.shufersal_id": "P_7290112339874"
    },
    "update": {
      "$set": {
        "name_en": "Strawberry",
        "aliases.en": [
          "Strawberry"
        ],
        "aliases.ar": []
      }
    }
  },
  {
    "filter": {
      "metadata.shufersal_id": "P_7290112347008"
    },
    "update": {
      "$set": {
        "name_en": "Strawberry",
        "aliases.en": [
          "Strawberry"
        ],
        "aliases.ar": []
      }
    }
  },
  {
    "filter": {
      "metadata.shufersal_id": "P_7290112355102"
    },
    "update": {
      "$set": {
        "name_en": "",
        "aliases.en": [
          ""
        ],
        "aliases.ar": []
      }
    }
  },
  {
    "filter": {
      "metadata.shufersal_id": "P_7290110561604"
    },
    "update": {
      "$set": {
        "name_en": "Strawberry",
        "aliases.en": [
          "Strawberry"
        ],
        "aliases.ar": []
      }
    }
  },
  {
    "filter": {
      "metadata.shufersal_id": "P_58030"
    },
    "update": {
      "$set": {
        "name_en": "Yoplait Strawberry",
        "aliases.en": [
          "Yoplait Strawberry"
        ],
        "aliases.ar": [],
        "brand_en": "Yoplait"
      }
    }
  },
  {
    "filter": {
      "metadata.shufersal_id": "P_7290110322946"
    },
    "update": {
      "$set": {
        "name_en": "Yoplait Strawberry",
        "aliases.en": [
          "Yoplait Strawberry"
        ],
        "aliases.ar": [],
        "brand_en": "Yoplait"
      }
    }
  },
  {
    "filter": {
      "metadata.shufersal_id": "P_7290110324551"
    },
    "update": {
      "$set": {
        "name_en": "Yoplait Strawberry",
        "aliases.en": [
          "Yoplait Strawberry"
        ],
        "aliases.ar": [],
        "brand_en": "Yoplait"
      }
    }
  },
  {
    "filter": {
      "metadata.shufersal_id": "P_7290110325510"
    },
    "update": {
      "$set": {
        "name_en": "Yoplait Vanilla",
        "aliases.en": [
          "Yoplait Vanilla"
        ],
        "aliases.ar": [],
        "brand_en": "Yoplait"
      }
    }
  },
  {
    "filter": {
      "metadata.shufersal_id": "P_7290110326890"
    },
    "update": {
      "$set": {
        "name_en": "Yoplait Strawberry",
        "aliases.en": [
          "Yoplait Strawberry"
        ],
        "aliases.ar": [],
        "brand_en": "Yoplait"
      }
    }
  },
  {
    "filter": {
      "metadata.shufersal_id": "P_7290010472307"
    },
    "update": {
      "$set": {
        "name_en": "Strawberry",
        "aliases.en": [
          "Strawberry"
        ],
        "aliases.ar": []
      }
    }
  },
  {
    "filter": {
      "metadata.shufersal_id": "P_7290110576851"
    },
    "update": {
      "$set": {
        "name_en": "",
        "aliases.en": [
          ""
        ],
        "aliases.ar": []
      }
    }
  },
  {
    "filter": {
      "metadata.shufersal_id": "P_4584306"
    },
    "update": {
      "$set": {
        "name_en": "Strawberry",
        "aliases.en": [
          "Strawberry"
        ],
        "aliases.ar": []
      }
    }
  },
  {
    "filter": {
      "metadata.shufersal_id": "P_6664037"
    },
    "update": {
      "$set": {
        "name_en": "Strawberry /",
        "aliases.en": [
          "Strawberry /"
        ],
        "aliases.ar": []
      }
    }
  },
  {
    "filter": {
      "metadata.shufersal_id": "P_7290014762220"
    },
    "update": {
      "$set": {
        "name_en": "'",
        "aliases.en": [
          "'"
        ],
        "aliases.ar": []
      }
    }
  },
  {
    "filter": {
      "metadata.shufersal_id": "P_4136857"
    },
    "update": {
      "$set": {
        "name_en": "'",
        "aliases.en": [
          "'"
        ],
        "aliases.ar": []
      }
    }
  },
  {
    "filter": {
      "metadata.shufersal_id": "P_7290116934242"
    },
    "update": {
      "$set": {
        "name_en": "' Tnuva Pineapple",
        "aliases.en": [
          "' Tnuva Pineapple"
        ],
        "aliases.ar": []
      }
    }
  },
  {
    "filter": {
      "metadata.shufersal_id": "P_7290116934556"
    },
    "update": {
      "$set": {
        "name_en": "' Tnuva Peach",
        "aliases.en": [
          "' Tnuva Peach"
        ],
        "aliases.ar": []
      }
    }
  },
  {
    "filter": {
      "metadata.shufersal_id": "P_7290110565435"
    },
    "update": {
      "$set": {
        "name_en": "Milk",
        "aliases.en": [
          "Milk"
        ],
        "aliases.ar": []
      }
    }
  },
  {
    "filter": {
      "metadata.shufersal_id": "P_554402"
    },
    "update": {
      "$set": {
        "name_en": "",
        "aliases.en": [
          ""
        ],
        "aliases.ar": []
      }
    }
  },
  {
    "filter": {
      "metadata.shufersal_id": "P_5431883"
    },
    "update": {
      "$set": {
        "name_en": "Milk",
        "aliases.en": [
          "Milk"
        ],
        "aliases.ar": []
      }
    }
  },
  {
    "filter": {
      "metadata.shufersal_id": "P_5431913"
    },
    "update": {
      "$set": {
        "name_en": "Cheese",
        "aliases.en": [
          "Cheese"
        ],
        "aliases.ar": []
      }
    }
  },
  {
    "filter": {
      "metadata.shufersal_id": "P_5431890"
    },
    "update": {
      "$set": {
        "name_en": "",
        "aliases.en": [
          ""
        ],
        "aliases.ar": []
      }
    }
  },
  {
    "filter": {
      "metadata.shufersal_id": "P_5431906"
    },
    "update": {
      "$set": {
        "name_en": "",
        "aliases.en": [
          ""
        ],
        "aliases.ar": []
      }
    }
  },
  {
    "filter": {
      "metadata.shufersal_id": "P_5431937"
    },
    "update": {
      "$set": {
        "name_en": "",
        "aliases.en": [
          ""
        ],
        "aliases.ar": []
      }
    }
  },
  {
    "filter": {
      "metadata.shufersal_id": "P_5431968"
    },
    "update": {
      "$set": {
        "name_en": "Cream",
        "aliases.en": [
          "Cream"
        ],
        "aliases.ar": []
      }
    }
  },
  {
    "filter": {
      "metadata.shufersal_id": "P_7290106654099"
    },
    "update": {
      "$set": {
        "name_en": "",
        "aliases.en": [
          ""
        ],
        "aliases.ar": []
      }
    }
  },
  {
    "filter": {
      "metadata.shufersal_id": "P_7290107957991"
    },
    "update": {
      "$set": {
        "name_en": "Milk",
        "aliases.en": [
          "Milk"
        ],
        "aliases.ar": []
      }
    }
  },
  {
    "filter": {
      "metadata.shufersal_id": "P_7290106663121"
    },
    "update": {
      "$set": {
        "name_en": "",
        "aliases.en": [
          ""
        ],
        "aliases.ar": []
      }
    }
  },
  {
    "filter": {
      "metadata.shufersal_id": "P_522326"
    },
    "update": {
      "$set": {
        "name_en": "Fresh Milk 1% Fat",
        "aliases.en": [
          "Fresh Milk 1% Fat"
        ],
        "aliases.ar": []
      }
    }
  },
  {
    "filter": {
      "metadata.shufersal_id": "P_7290019790259"
    },
    "update": {
      "$set": {
        "name_en": "Milk Natural 4% Fat Fat",
        "aliases.en": [
          "Milk Natural 4% Fat Fat"
        ],
        "aliases.ar": []
      }
    }
  },
  {
    "filter": {
      "metadata.shufersal_id": "P_7290019790358"
    },
    "update": {
      "$set": {
        "name_en": "Milk Enriched Lactose 2% Fat",
        "aliases.en": [
          "Milk Enriched Lactose 2% Fat"
        ],
        "aliases.ar": []
      }
    }
  },
  {
    "filter": {
      "metadata.shufersal_id": "P_7290019790303"
    },
    "update": {
      "$set": {
        "name_en": "Milk Enriched 3% Fat Fat",
        "aliases.en": [
          "Milk Enriched 3% Fat Fat"
        ],
        "aliases.ar": []
      }
    }
  },
  {
    "filter": {
      "metadata.shufersal_id": "P_7290107932080"
    },
    "update": {
      "$set": {
        "name_en": "Milk Yotvata Enriched3% Fat Bottle",
        "aliases.en": [
          "Milk Yotvata Enriched3% Fat Bottle"
        ],
        "aliases.ar": []
      }
    }
  },
  {
    "filter": {
      "metadata.shufersal_id": "P_40974"
    },
    "update": {
      "$set": {
        "name_en": "Fresh Milk 2% Fat Low Lactose",
        "aliases.en": [
          "Fresh Milk 2% Fat Low Lactose"
        ],
        "aliases.ar": []
      }
    }
  },
  {
    "filter": {
      "metadata.shufersal_id": "P_7290116930695"
    },
    "update": {
      "$set": {
        "name_en": "Milk Lactose 2% Fat Mehadrin",
        "aliases.en": [
          "Milk Lactose 2% Fat Mehadrin"
        ],
        "aliases.ar": []
      }
    }
  },
  {
    "filter": {
      "metadata.shufersal_id": "P_51352"
    },
    "update": {
      "$set": {
        "name_en": "Milk 4% Fat-3.6% Fat",
        "aliases.en": [
          "Milk 4% Fat-3.6% Fat"
        ],
        "aliases.ar": []
      }
    }
  },
  {
    "filter": {
      "metadata.shufersal_id": "P_7290114311328"
    },
    "update": {
      "$set": {
        "name_en": "Milk Lactose Enriched 2% Fat",
        "aliases.en": [
          "Milk Lactose Enriched 2% Fat"
        ],
        "aliases.ar": []
      }
    }
  },
  {
    "filter": {
      "metadata.shufersal_id": "P_7290114310239"
    },
    "update": {
      "$set": {
        "name_en": "Milk Lactose Enriched2% Fat",
        "aliases.en": [
          "Milk Lactose Enriched2% Fat"
        ],
        "aliases.ar": []
      }
    }
  },
  {
    "filter": {
      "metadata.shufersal_id": "P_3029815"
    },
    "update": {
      "$set": {
        "name_en": "Milk Enriched Yotvata 3% Fat",
        "aliases.en": [
          "Milk Enriched Yotvata 3% Fat"
        ],
        "aliases.ar": []
      }
    }
  },
  {
    "filter": {
      "metadata.shufersal_id": "P_7290114311458"
    },
    "update": {
      "$set": {
        "name_en": "Milk Enriched +D Carton3% Fat",
        "aliases.en": [
          "Milk Enriched +D Carton3% Fat"
        ],
        "aliases.ar": []
      }
    }
  },
  {
    "filter": {
      "metadata.shufersal_id": "P_7290114313018"
    },
    "update": {
      "$set": {
        "name_en": "Milk Lactose Vanilla 2% Fat",
        "aliases.en": [
          "Milk Lactose Vanilla 2% Fat"
        ],
        "aliases.ar": []
      }
    }
  },
  {
    "filter": {
      "metadata.shufersal_id": "P_7290116935416"
    },
    "update": {
      "$set": {
        "name_en": "Milk Whipping 2% Fat",
        "aliases.en": [
          "Milk Whipping 2% Fat"
        ],
        "aliases.ar": []
      }
    }
  },
  {
    "filter": {
      "metadata.shufersal_id": "P_7290014758162"
    },
    "update": {
      "$set": {
        "name_en": "Milk 3.6% Fat",
        "aliases.en": [
          "Milk 3.6% Fat"
        ],
        "aliases.ar": []
      }
    }
  },
  {
    "filter": {
      "metadata.shufersal_id": "P_7290102392094"
    },
    "update": {
      "$set": {
        "name_en": "Milk Carton 4.1% Fat",
        "aliases.en": [
          "Milk Carton 4.1% Fat"
        ],
        "aliases.ar": []
      }
    }
  },
  {
    "filter": {
      "metadata.shufersal_id": "P_1201602"
    },
    "update": {
      "$set": {
        "name_en": "Eggs Packaged L",
        "aliases.en": [
          "Eggs Packaged L"
        ],
        "aliases.ar": []
      }
    }
  },
  {
    "filter": {
      "metadata.shufersal_id": "P_7296073224679"
    },
    "update": {
      "$set": {
        "name_en": "Organic L",
        "aliases.en": [
          "Organic L"
        ],
        "aliases.ar": []
      }
    }
  },
  {
    "filter": {
      "metadata.shufersal_id": "P_7296073236139"
    },
    "update": {
      "$set": {
        "name_en": "Eggs Organic XL",
        "aliases.en": [
          "Eggs Organic XL"
        ],
        "aliases.ar": []
      }
    }
  }
]